LICENSE
boringit/__init__.py
boringit/boringit.py
boringit-0.1.1.dist-info/entry_points.txt
boringit-0.1.1.dist-info/LICENSE
boringit-0.1.1.dist-info/WHEEL
boringit-0.1.1.dist-info/METADATA
boringit-0.1.1.dist-info/RECORD
