Metadata-Version: 2.1
Name: boringit
Version: 0.1.1
Summary: A tool to optimize git Add, Commit and Push routine.
Home-page: https://github.com/marcusmello/boringit
License: MIT
Keywords: git,git flow,productivity
Author: marcusmello
Author-email: marcus@vintem.tech
Requires-Python: >=3.8,<4.0
Classifier: License :: OSI Approved :: MIT License
Classifier: Programming Language :: Python :: 3
Classifier: Programming Language :: Python :: 3.8
Requires-Dist: pyyaml (>=5.3.1,<6.0.0)
Project-URL: Repository, https://gitlab.com/marcusmello/boringit
